{
    "resourceType": "Patient",
    "name": [
        {
            "use": "official",
            "family": "Short",
            "given": ["Shane", "Anthony"]
        }
    ],
    "gender": "male",
    "birthDate": "1996-07-24",
    "telecom": [
        {
            "value": "1234567890",
            "use": "mobile",
            "system": "phone"
        },
        {
            "value": "+353123456789",
            "use": "old",
            "system": "phone"
        },
        {
            "value": "demo.email@gmail.com",
            "system": "email"
        }
    ],
    "address": [
        {
            "use": "home",
            "line": [
                "Unit 1, 2 Fleet Street"
            ],
            "city": "Townville",
            "state": "Ontario",
            "country": "Canada",
            "postalCode": "1234",
            "type": "both"
            
        }
    ]

}